{
  "run_id": "0bfc674c-af95-4b29-879d-5c6b2aeeb044",
  "timestamp": "2026-05-17T01:40:41.986893",
  "scenario": "pmo",
  "duration": 3600.0,
  "num_points": 361,
  "environment_params": {
    "Estrogen": 0.28392867522973253,
    "PTH": 51.627811842872035,
    "k_prod_Scl": 8.20426734674227e-06,
    "k_deg_Scl": 7.597981773334985e-05,
    "Sclerostin_bone": 0.09097229947370289,
    "k_prod_RANKL": 1.4720477967319692e-05,
    "k_deg_RANKL": 1.8750493173482028e-05,
    "RANKL_bone": 1.2924067589727641,
    "k_prod_OPG": 6.851738782353453e-05,
    "k_deg_OPG": 2.5512200139567763e-05,
    "OPG_bone": 6.070117533032232,
    "MineralIon": 2.090065072531019,
    "k_prod_Mineral": 0.10427788904745978,
    "k_loss_Mineral": 0.05762104596472862
  },
  "biosensor_config": {
    "circuit_type": "amplifying",
    "sensitivity": 16.296815627340887,
    "threshold": 0.0003640725377645652,
    "dynamic_range": [
      0.0,
      9.56201802894681
    ],
    "kd": 0.01777368908093936,
    "response_type": "hill",
    "receptor_concentration": 1.4786001649333969,
    "enzyme_concentration": 19.742814252928834,
    "amplification_gain": 900.5309615944138,
    "response_time": 131.87947277826555
  },
  "biosensor_type": "amplifying",
  "noise_preset": "medium",
  "noise_params": {
    "additive_sigma": 0.03,
    "multiplicative_sigma": 0.06,
    "drift_rate": 0.0002,
    "outlier_probability": 0.003,
    "outlier_magnitude": 4.0,
    "shot_noise_enabled": false,
    "seed": null
  },
  "measurement": {
    "snr_db": 22.53831238418893,
    "n_detections": 361,
    "detection_rate": 1.0,
    "time_to_detection": 1922.2251592154412,
    "false_negative_rate": 0.0,
    "max_signal": 11.430034134535358,
    "mean_signal": 9.909436688006352,
    "signal_std": 0.8000683211958919,
    "has_noise": true
  },
  "signal_to_noise_ratio_SNR": 22.53831238418893,
  "time_to_detection_threshold": 1922.2251592154412,
  "false_negative_rate": 0.0,
  "dynamic_range_of_output": 0.0,
  "sclerostin_mean": 1.1467464591804943,
  "sclerostin_max": 1.4995346358465402,
  "sclerostin_min": 0.025000000000000005,
  "sclerostin_std": 0.18907050851281382,
  "sclerostin_change": 