{
  "run_id": "1c1a2142-1aed-4ad9-853f-0e850d06727c",
  "timestamp": "2026-01-31T04:09:47.848483",
  "scenario": "ckd_mbd",
  "duration": 3600.0,
  "num_points": 361,
  "environment_params": {
    "Estrogen": 0.5786654106163571,
    "PTH": 333.1031165732305,
    "k_prod_Scl": 1.3359786206471352e-05,
    "k_deg_Scl": 4.408427099139609e-05,
    "k_prod_RANKL": 1.618087330718057e-05,
    "k_prod_OPG": 5.2326264785376486e-05,
    "Sclerostin_bone": 0.3293374045354738,
    "RANKL_bone": 0.6904748463890964,
    "OPG_bone": 4.281093409767475,
    "MineralIon": 3.158617810197092,
    "k_prod_Mineral": 0.17267222949895814
  },
  "biosensor_config": {
    "circuit_type": "threshold",
    "sensitivity": 8.65620500160885,
    "threshold": 5.324729340110925e-05,
    "dynamic_range": [
      0.0,
      2.6284585922567243
    ],
    "kd": 0.8803400274152201,
    "response_type": "linear",
    "hill_coefficient": 4.070776001972462,
    "off_level": 0.7186982614634623,
    "on_level": 15.985570267943537
  },
  "noise_preset": "low",
  "noise_params": {
    "additive_sigma": 0.005,
    "multiplicative_sigma": 0.01,
    "drift_rate": 2e-05,
    "outlier_probability": 0.0002,
    "outlier_magnitude": 2.0,
    "shot_noise_enabled": false,
    "seed": null
  },
  "measurement": {
    "snr_db": 34.544999246652736,
    "n_detections": 361,
    "detection_rate": 1.0,
    "time_to_detection": 1333.7695457795671,
    "false_negative_rate": 0.0102935985426611,
    "max_signal": 2.749519408366902,
    "mean_signal": 2.65889155285737,
    "signal_std": 0.1075939811729344,
    "has_noise": true
  },
  "false_negative_rate": 0.0102935985426611,
  "sclerostin_mean": 3.4678013840000044,
  "sclerostin_max": 3.8786874977850805,
  "sclerostin_min": 0.025000000000000005,
  "sclerostin_std": 0.2743830108264068,
  "metadata_file": "metadata/1c1a2142-1aed-4ad9-853f-0e850d06727c.json",
  "timeseries_file": "timeseries/1c1a2142-1aed-4ad9-853f-0e850d06727c.csv"
}