{
  "run_id": "2a5f8383-ae44-4dd5-af27-e8176ef6a848",
  "timestamp": "2026-05-17T01:40:36.621587",
  "scenario": "ckd_mbd",
  "duration": 3600.0,
  "num_points": 361,
  "environment_params": {
    "Estrogen": 1.1191819655410318,
    "PTH": 139.82011971011735,
    "k_prod_Scl": 8.434313027991512e-06,
    "k_deg_Scl": 4.029331193499684e-05,
    "Sclerostin_bone": 0.2093647294502031,
    "k_prod_RANKL": 1.8699976987417896e-05,
    "k_deg_RANKL": 1.9112549899203564e-05,
    "RANKL_bone": 0.5584446576717503,
    "k_prod_OPG": 7.705894822254589e-05,
    "k_deg_OPG": 2.107021511054966e-05,
    "OPG_bone": 5.342712609864146,
    "MineralIon": 3.980575202980097,
    "k_prod_Mineral": 0.15376950390395783,
    "k_loss_Mineral": 0.033902821368564755
  },
  "biosensor_config": {
    "circuit_type": "direct_binding",
    "sensitivity": 1.7499828125154149,
    "threshold": 0.00018868837731638973,
    "dynamic_range": [
      0.0,
      2.5456164188019863
    ],
    "kd": 4.08146736293338,
    "response_type": "linear",
    "receptor_concentration": 1.1159929561134352,
    "kon": 149961.17801631507,
    "koff": 612061.6537806327
  },
  "biosensor_type": "direct_binding",
  "noise_preset": "medium",
  "noise_params": {
    "additive_sigma": 0.03,
    "multiplicative_sigma": 0.06,
    "drift_rate": 0.0002,
    "outlier_probability": 0.003,
    "outlier_magnitude": 4.0,
    "shot_noise_enabled": false,
    "seed": null
  },
  "measurement": {
    "snr_db": 3.9259243968000113,
    "n_detections": 360,
    "detection_rate": 0.997229916897507,
    "time_to_detection": 5025.420927413695,
    "false_negative_rate": 0.01731264457743962,
    "max_signal": 1.5161471028571474,
    "mean_signal": 1.0233686332433978,
    "signal_std": 0.22994061270037344,
    "has_noise": true
  },
  "signal_to_noise_ratio_SNR": 3.9259243968000113,
  "time_to_detection_threshold": 5025.420927413695,
  "false_negative_rate": 0.01731264457743962,
  "dynamic_range_of_output": 0.0,
  "sclerostin_mean": 2.0925030904201405,
  "sclerostin_max": 2.1854021718017957,
  "sclerostin_min": 0.025000000000000005,
  "sclerostin_std": 0.11770343038944052,
  "sclerostin_change": 