{
  "run_id": "3512e765-1159-4277-a051-0da25157345d",
  "timestamp": "2026-01-31T04:10:32.566341",
  "scenario": "pmo",
  "duration": 3600.0,
  "num_points": 361,
  "environment_params": {
    "Estrogen": 0.1669877069354163,
    "PTH": 59.18070659554319,
    "k_prod_Scl": 6.835001394050338e-06,
    "k_prod_RANKL": 2.43725148883799e-05,
    "k_prod_OPG": 5.0599614937144846e-05,
    "Sclerostin_bone": 0.09257925185365509,
    "RANKL_bone": 1.5122174034029674,
    "OPG_bone": 2.1439492706623366
  },
  "biosensor_config": {
    "circuit_type": "amplifying",
    "sensitivity": 2.168356515328138,
    "threshold": 0.004272951927124137,
    "dynamic_range": [
      0.0,
      16.500575939706092
    ],
    "kd": 0.34402586022356874,
    "response_type": "michaelis_menten",
    "receptor_concentration": 0.7923510659541464,
    "enzyme_concentration": 3.0582660165317543,
    "amplification_gain": 5034.124792222269,
    "response_time": 368.83695555641657
  },
  "noise_preset": "high",
  "noise_params": {
    "additive_sigma": 0.1,
    "multiplicative_sigma": 0.2,
    "drift_rate": 0.001,
    "outlier_probability": 0.01,
    "outlier_magnitude": 10.0,
    "shot_noise_enabled": true,
    "seed": null
  },
  "measurement": {
    "snr_db": 0.31768280612918376,
    "n_detections": 360,
    "detection_rate": 0.997229916897507,
    "time_to_detection": 1708.1766800037306,
    "false_negative_rate": 0.09438254491164938,
    "max_signal": 6.542544948635971,
    "mean_signal": 3.9348481101347996,
    "signal_std": 1.1179611243782541,
    "has_noise": true
  },
  "false_negative_rate": 0.09438254491164938,
  "sclerostin_mean": 1.1670783608228372,
  "sclerostin_max": 1.5262269907760344,
  "sclerostin_min": 0.025000000000000005,
  "sclerostin_std": 0.19251802143981836,
  "metadata_file": "metadata/3512e765-1159-4277-a051-0da25157345d.json",
  "timeseries_file": "timeseries/3512e765-1159-4277-a051-0da25157345d.csv"
}