{
  "run_id": "49dc6e3d-9632-4806-a01c-df7aae376bf1",
  "timestamp": "2026-01-31T04:09:50.558752",
  "scenario": "pmo",
  "duration": 3600.0,
  "num_points": 361,
  "environment_params": {
    "Estrogen": 0.17072199951975045,
    "PTH": 51.714595748038604,
    "k_prod_Scl": 7.216819537472867e-06,
    "k_prod_RANKL": 2.2356331902395705e-05,
    "k_prod_OPG": 5.147598599834369e-05,
    "Sclerostin_bone": 0.0855913966625837,
    "RANKL_bone": 2.318246930128094,
    "OPG_bone": 2.122334625508373
  },
  "biosensor_config": {
    "circuit_type": "ratiometric",
    "sensitivity": 2.851373739127224,
    "threshold": 0.016027789717114528,
    "dynamic_range": [
      0.0,
      5.199442360612835
    ],
    "kd": 0.059641481258003365,
    "response_type": "hill",
    "reference_kd": 0.30727582149422766,
    "ratio_exponent": 2.7599322736122995
  },
  "noise_preset": "medium",
  "noise_params": {
    "additive_sigma": 0.03,
    "multiplicative_sigma": 0.06,
    "drift_rate": 0.0003,
    "outlier_probability": 0.003,
    "outlier_magnitude": 4.0,
    "shot_noise_enabled": false,
    "seed": null
  },
  "measurement": {
    "snr_db": 12.920549627027203,
    "n_detections": 361,
    "detection_rate": 1.0,
    "time_to_detection": 1485.8298785898046,
    "false_negative_rate": 0.0394724554296675,
    "max_signal": 4.157610891325904,
    "mean_signal": 3.386899639252684,
    "signal_std": 0.35807402786297277,
    "has_noise": true
  },
  "false_negative_rate": 0.0394724554296675,
  "sclerostin_mean": 1.1090879526873807,
  "sclerostin_max": 1.480414034300284,
  "sclerostin_min": 0.025000000000000005,
  "sclerostin_std": 0.19766362107774565,
  "metadata_file": "metadata/49dc6e3d-9632-4806-a01c-df7aae376bf1.json",
  "timeseries_file": "timeseries/49dc6e3d-9632-4806-a01c-df7aae376bf1.csv"
}