{
  "run_id": "4b7a6be4-0d10-44c6-b650-63668ef531d7",
  "timestamp": "2026-01-31T04:10:04.162538",
  "scenario": "ckd_mbd",
  "duration": 3600.0,
  "num_points": 361,
  "environment_params": {
    "Estrogen": 1.3798714906047949,
    "PTH": 330.0762976627116,
    "k_prod_Scl": 1.9703602929385042e-05,
    "k_deg_Scl": 3.769997869937215e-05,
    "k_prod_RANKL": 2.460124792037968e-05,
    "k_prod_OPG": 0.00010361388311753811,
    "Sclerostin_bone": 0.41724036897397054,
    "RANKL_bone": 1.1514588281016482,
    "OPG_bone": 3.580621940016647,
    "MineralIon": 2.460520012407426,
    "k_prod_Mineral": 0.1946512681348914
  },
  "biosensor_config": {
    "circuit_type": "ratiometric",
    "sensitivity": 6.649237950259716,
    "threshold": 0.0013614192575175117,
    "dynamic_range": [
      0.0,
      16.79971642466361
    ],
    "kd": 0.41982815290046793,
    "response_type": "linear",
    "reference_kd": 0.3028209023744899,
    "ratio_exponent": 1.0862493492877094
  },
  "noise_preset": "low",
  "noise_params": {
    "additive_sigma": 0.005,
    "multiplicative_sigma": 0.01,
    "drift_rate": 2e-05,
    "outlier_probability": 0.0002,
    "outlier_magnitude": 2.0,
    "shot_noise_enabled": false,
    "seed": null
  },
  "measurement": {
    "snr_db": 39.75610092417022,
    "n_detections": 361,
    "detection_rate": 1.0,
    "time_to_detection": 2621.179871098535,
    "false_negative_rate": 0.013173826328333988,
    "max_signal": 17.30361024820688,
    "mean_signal": 16.83333712775918,
    "signal_std": 0.16947875672151616,
    "has_noise": true
  },
  "false_negative_rate": 0.013173826328333988,
  "sclerostin_mean": 4.132390271178939,
  "sclerostin_max": 4.297852298062565,
  "sclerostin_min": 0.025000000000000005,
  "sclerostin_std": 0.23032002523619488,
  "metadata_file": "metadata/4b7a6be4-0d10-44c6-b650-63668ef531d7.json",
  "timeseries_file": "timeseries/4b7a6be4-0d10-44c6-b650-63668ef531d7.csv"
}