{
  "run_id": "4bd8837a-763c-4974-8750-8a50b7a720c1",
  "timestamp": "2026-01-31T04:10:18.717737",
  "scenario": "ckd_mbd",
  "duration": 3600.0,
  "num_points": 361,
  "environment_params": {
    "Estrogen": 0.5926498105269168,
    "PTH": 305.1745352766627,
    "k_prod_Scl": 1.3357222116223098e-05,
    "k_deg_Scl": 3.3138993825116705e-05,
    "k_prod_RANKL": 1.4248116240218255e-05,
    "k_prod_OPG": 7.474107702139526e-05,
    "Sclerostin_bone": 0.2445990431885329,
    "RANKL_bone": 1.5224588480244412,
    "OPG_bone": 4.477600798949311,
    "MineralIon": 3.7230174425226905,
    "k_prod_Mineral": 0.17179422730022662
  },
  "biosensor_config": {
    "circuit_type": "amplifying",
    "sensitivity": 8.024325245678012,
    "threshold": 0.0002476111914928967,
    "dynamic_range": [
      0.0,
      7.411305926760625
    ],
    "kd": 0.7059996836826378,
    "response_type": "linear",
    "receptor_concentration": 3.5514566482698235,
    "enzyme_concentration": 8.257275561687894,
    "amplification_gain": 6683.170099444132,
    "response_time": 323.24298709944367
  },
  "noise_preset": "medium",
  "noise_params": {
    "additive_sigma": 0.03,
    "multiplicative_sigma": 0.06,
    "drift_rate": 0.0003,
    "outlier_probability": 0.003,
    "outlier_magnitude": 4.0,
    "shot_noise_enabled": false,
    "seed": null
  },
  "measurement": {
    "snr_db": 19.674341657653063,
    "n_detections": 361,
    "detection_rate": 1.0,
    "time_to_detection": 1600.3131085649516,
    "false_negative_rate": 0.049388557307345725,
    "max_signal": 9.837014014459138,
    "mean_signal": 7.936877361261888,
    "signal_std": 0.6822911620587722,
    "has_noise": true
  },
  "false_negative_rate": 0.049388557307345725,
  "sclerostin_mean": 2.650129618999988,
  "sclerostin_max": 3.049916281962007,
  "sclerostin_min": 0.025000000000000005,
  "sclerostin_std": 0.2444138014572497,
  "metadata_file": "metadata/4bd8837a-763c-4974-8750-8a50b7a720c1.json",
  "timeseries_file": "timeseries/4bd8837a-763c-4974-8750-8a50b7a720c1.csv"
}