{
  "run_id": "6ba5942f-8e58-4022-86b1-df4f3cd128b4",
  "timestamp": "2026-01-31T04:10:24.567869",
  "scenario": "pmo",
  "duration": 3600.0,
  "num_points": 361,
  "environment_params": {
    "Estrogen": 0.19783297722150342,
    "PTH": 54.69831527354567,
    "k_prod_Scl": 5.227013029594063e-06,
    "k_prod_RANKL": 2.8844333386965465e-05,
    "k_prod_OPG": 5.7901582409668554e-05,
    "Sclerostin_bone": 0.03189280862351641,
    "RANKL_bone": 1.2001007548378313,
    "OPG_bone": 3.394587948597449
  },
  "biosensor_config": {
    "circuit_type": "threshold",
    "sensitivity": 13.703300520275612,
    "threshold": 0.0025733137017092626,
    "dynamic_range": [
      0.0,
      10.774324124906867
    ],
    "kd": 1.288992728700197,
    "response_type": "hill",
    "hill_coefficient": 4.240100957640276,
    "off_level": 0.716507339562521,
    "on_level": 13.93679168371659
  },
  "noise_preset": "medium",
  "noise_params": {
    "additive_sigma": 0.03,
    "multiplicative_sigma": 0.06,
    "drift_rate": 0.0003,
    "outlier_probability": 0.003,
    "outlier_magnitude": 4.0,
    "shot_noise_enabled": false,
    "seed": null
  },
  "measurement": {
    "snr_db": 5.33950968603821,
    "n_detections": 361,
    "detection_rate": 1.0,
    "time_to_detection": 4628.978780388476,
    "false_negative_rate": 0.09538472135415295,
    "max_signal": 3.2629657849144946,
    "mean_signal": 1.6497235593369661,
    "signal_std": 0.6797202475752074,
    "has_noise": true
  },
  "false_negative_rate": 0.09538472135415295,
  "sclerostin_mean": 0.5167358994947762,
  "sclerostin_max": 0.7782399457829516,
  "sclerostin_min": 0.025000000000000005,
  "sclerostin_std": 0.136168852132538,
  "metadata_file": "metadata/6ba5942f-8e58-4022-86b1-df4f3cd128b4.json",
  "timeseries_file": "timeseries/6ba5942f-8e58-4022-86b1-df4f3cd128b4.csv"
}