{
  "run_id": "6f1211e1-7141-4751-a3fe-6e8d3ea1f7ea",
  "timestamp": "2026-01-31T04:09:59.857145",
  "scenario": "pmo",
  "duration": 3600.0,
  "num_points": 361,
  "environment_params": {
    "Estrogen": 0.09446497634211182,
    "PTH": 80.00535598602622,
    "k_prod_Scl": 8.871618743793874e-06,
    "k_prod_RANKL": 4.0230663462016235e-05,
    "k_prod_OPG": 6.32522940887381e-05,
    "Sclerostin_bone": 0.07800137744449537,
    "RANKL_bone": 2.480265606488987,
    "OPG_bone": 1.9511520815482588
  },
  "biosensor_config": {
    "circuit_type": "ratiometric",
    "sensitivity": 5.986984061227672,
    "threshold": 7.084231414859877e-05,
    "dynamic_range": [
      0.0,
      14.182430596911518
    ],
    "kd": 0.09512954097605672,
    "response_type": "michaelis_menten",
    "reference_kd": 0.29347365577427686,
    "ratio_exponent": 1.1537366177681685
  },
  "noise_preset": "high",
  "noise_params": {
    "additive_sigma": 0.1,
    "multiplicative_sigma": 0.2,
    "drift_rate": 0.001,
    "outlier_probability": 0.01,
    "outlier_magnitude": 10.0,
    "shot_noise_enabled": true,
    "seed": null
  },
  "measurement": {
    "snr_db": 7.922143099506486,
    "n_detections": 361,
    "detection_rate": 1.0,
    "time_to_detection": 1788.2403040465001,
    "false_negative_rate": 0.11106314667963642,
    "max_signal": 11.78477551578317,
    "mean_signal": 7.839600463161227,
    "signal_std": 1.5193306793149721,
    "has_noise": true
  },
  "false_negative_rate": 0.11106314667963642,
  "sclerostin_mean": 1.1457831651524204,
  "sclerostin_max": 1.669293266103226,
  "sclerostin_min": 0.025000000000000005,
  "sclerostin_std": 0.2738664554628151,
  "metadata_file": "metadata/6f1211e1-7141-4751-a3fe-6e8d3ea1f7ea.json",
  "timeseries_file": "timeseries/6f1211e1-7141-4751-a3fe-6e8d3ea1f7ea.csv"
}