{
  "run_id": "756bb151-0179-4eca-9929-2c7035361818",
  "timestamp": "2026-01-31T04:09:43.638427",
  "scenario": "healthy",
  "duration": 3600.0,
  "num_points": 361,
  "environment_params": {
    "Estrogen": 0.6173592199317665,
    "PTH": 45.60045015066787,
    "k_prod_Scl": 3.1599377255425504e-06,
    "k_prod_RANKL": 1.0956331329541277e-05,
    "k_prod_OPG": 0.00010689693613710142,
    "Sclerostin_bone": 0.04811486222417054,
    "RANKL_bone": 0.5812731636718261,
    "OPG_bone": 8.924180295280978
  },
  "biosensor_config": {
    "circuit_type": "direct_binding",
    "sensitivity": 6.346560866301325,
    "threshold": 0.00010597125055863098,
    "dynamic_range": [
      0.0,
      19.070431029592495
    ],
    "kd": 4.960484610750889,
    "response_type": "hill",
    "receptor_concentration": 4.672516942050521,
    "kon": 725692.0380309758,
    "koff": 3599784.186797105
  },
  "noise_preset": "high",
  "noise_params": {
    "additive_sigma": 0.1,
    "multiplicative_sigma": 0.2,
    "drift_rate": 0.001,
    "outlier_probability": 0.01,
    "outlier_magnitude": 10.0,
    "shot_noise_enabled": true,
    "seed": null
  },
  "measurement": {
    "snr_db": -31.834691594988126,
    "n_detections": 359,
    "detection_rate": 0.9944598337950139,
    "time_to_detection": 7050.215841706192,
    "false_negative_rate": 0.12535941522128669,
    "max_signal": 4.237882505954973,
    "mean_signal": 1.8596471613604095,
    "signal_std": 1.0648615146010318,
    "has_noise": true
  },
  "false_negative_rate": 0.12535941522128669,
  "sclerostin_mean": 0.5348997545448975,
  "sclerostin_max": 0.6056750681229909,
  "sclerostin_min": 0.025000000000000005,
  "sclerostin_std": 0.04459286174390377,
  "metadata_file": "metadata/756bb151-0179-4eca-9929-2c7035361818.json",
  "timeseries_file": "timeseries/756bb151-0179-4eca-9929-2c7035361818.csv"
}