{
  "run_id": "99344f3e-e69a-4c16-acfe-d403fb7adba8",
  "timestamp": "2026-01-31T04:10:30.058359",
  "scenario": "healthy",
  "duration": 3600.0,
  "num_points": 361,
  "environment_params": {
    "Estrogen": 0.9116512189816253,
    "PTH": 35.013130012131036,
    "k_prod_Scl": 4.8723921999566326e-06,
    "k_prod_RANKL": 9.756450413933264e-06,
    "k_prod_OPG": 0.00012830213967991017,
    "Sclerostin_bone": 0.047594800307725345,
    "RANKL_bone": 0.5204671309591544,
    "OPG_bone": 6.82549009711008
  },
  "biosensor_config": {
    "circuit_type": "direct_binding",
    "sensitivity": 1.4310036554367849,
    "threshold": 5.24895270970735e-05,
    "dynamic_range": [
      0.0,
      10.366365734129698
    ],
    "kd": 0.04834384918861837,
    "response_type": "hill",
    "receptor_concentration": 5.135327387595871,
    "kon": 55972.12339058874,
    "koff": 2705.9078919613607
  },
  "noise_preset": "low",
  "noise_params": {
    "additive_sigma": 0.005,
    "multiplicative_sigma": 0.01,
    "drift_rate": 2e-05,
    "outlier_probability": 0.0002,
    "outlier_magnitude": 2.0,
    "shot_noise_enabled": false,
    "seed": null
  },
  "measurement": {
    "snr_db": 30.371397394819798,
    "n_detections": 361,
    "detection_rate": 1.0,
    "time_to_detection": 1800.181348823044,
    "false_negative_rate": 0.0005180800465311086,
    "max_signal": 1.5280814163854215,
    "mean_signal": 1.4669725227752275,
    "signal_std": 0.023979043207867038,
    "has_noise": true
  },
  "false_negative_rate": 0.0005180800465311086,
  "sclerostin_mean": 0.5232415338001165,
  "sclerostin_max": 0.5848125424112524,
  "sclerostin_min": 0.025000000000000005,
  "sclerostin_std": 0.040518835812774996,
  "metadata_file": "metadata/99344f3e-e69a-4c16-acfe-d403fb7adba8.json",
  "timeseries_file": "timeseries/99344f3e-e69a-4c16-acfe-d403fb7adba8.csv"
}