{
  "run_id": "b16cbc5d-297e-4f27-adde-ba6400027ed8",
  "timestamp": "2026-01-31T04:10:00.776674",
  "scenario": "pmo",
  "duration": 3600.0,
  "num_points": 361,
  "environment_params": {
    "Estrogen": 0.14192960026120172,
    "PTH": 47.36377346419549,
    "k_prod_Scl": 3.6176894822076402e-06,
    "k_prod_RANKL": 2.223894824756857e-05,
    "k_prod_OPG": 3.684459175078068e-05,
    "Sclerostin_bone": 0.09518886018313441,
    "RANKL_bone": 1.6946667016014736,
    "OPG_bone": 2.1282640828978416
  },
  "biosensor_config": {
    "circuit_type": "ratiometric",
    "sensitivity": 5.577637965377703,
    "threshold": 0.016179768431408212,
    "dynamic_range": [
      0.0,
      14.110120747703283
    ],
    "kd": 4.0226920599417415,
    "response_type": "hill",
    "reference_kd": 0.46649269052698006,
    "ratio_exponent": 0.4880487727396202
  },
  "noise_preset": "high",
  "noise_params": {
    "additive_sigma": 0.1,
    "multiplicative_sigma": 0.2,
    "drift_rate": 0.001,
    "outlier_probability": 0.01,
    "outlier_magnitude": 10.0,
    "shot_noise_enabled": true,
    "seed": null
  },
  "measurement": {
    "snr_db": 5.553644623980612,
    "n_detections": 361,
    "detection_rate": 1.0,
    "time_to_detection": 2585.0932991111354,
    "false_negative_rate": 0.08536157072124971,
    "max_signal": 9.80163031924869,
    "mean_signal": 6.0468271424449345,
    "signal_std": 1.3889951851933897,
    "has_noise": true
  },
  "false_negative_rate": 0.08536157072124971,
  "sclerostin_mean": 1.0709226085868844,
  "sclerostin_max": 1.261285700437881,
  "sclerostin_min": 0.025000000000000005,
  "sclerostin_std": 0.11090957978167226,
  "metadata_file": "metadata/b16cbc5d-297e-4f27-adde-ba6400027ed8.json",
  "timeseries_file": "timeseries/b16cbc5d-297e-4f27-adde-ba6400027ed8.csv"
}