{
  "run_id": "b5ed6e96-7490-49c7-bf25-a6148586d543",
  "timestamp": "2026-01-31T04:10:55.379402",
  "scenario": "ckd_mbd",
  "duration": 3600.0,
  "num_points": 361,
  "environment_params": {
    "Estrogen": 0.5539124221861951,
    "PTH": 249.85715507826254,
    "k_prod_Scl": 1.621933363481355e-05,
    "k_deg_Scl": 4.0639064470811104e-05,
    "k_prod_RANKL": 2.2011249108966473e-05,
    "k_prod_OPG": 7.124603848031006e-05,
    "Sclerostin_bone": 0.18983316886615823,
    "RANKL_bone": 1.4363117383994661,
    "OPG_bone": 3.312105161463632,
    "MineralIon": 2.643510677497915,
    "k_prod_Mineral": 0.16076926504725952
  },
  "biosensor_config": {
    "circuit_type": "threshold",
    "sensitivity": 2.177835261190649,
    "threshold": 0.0013355127503928113,
    "dynamic_range": [
      0.0,
      2.05900532496073
    ],
    "kd": 0.022149361350135118,
    "response_type": "hill",
    "hill_coefficient": 7.450436475031645,
    "off_level": 0.37751326895546,
    "on_level": 17.90162193301389
  },
  "noise_preset": "low",
  "noise_params": {
    "additive_sigma": 0.005,
    "multiplicative_sigma": 0.01,
    "drift_rate": 2e-05,
    "outlier_probability": 0.0002,
    "outlier_magnitude": 2.0,
    "shot_noise_enabled": false,
    "seed": null
  },
  "measurement": {
    "snr_db": 32.96047572076891,
    "n_detections": 361,
    "detection_rate": 1.0,
    "time_to_detection": 3248.502849803579,
    "false_negative_rate": 0.03204431540496892,
    "max_signal": 2.1611892767274448,
    "mean_signal": 2.0946620015134454,
    "signal_std": 0.02954338616265455,
    "has_noise": true
  },
  "false_negative_rate": 0.03204431540496892,
  "sclerostin_mean": 2.208493523153775,
  "sclerostin_max": 2.7228821271891945,
  "sclerostin_min": 0.025000000000000005,
  "sclerostin_std": 0.2853017051010947,
  "metadata_file": "metadata/b5ed6e96-7490-49c7-bf25-a6148586d543.json",
  "timeseries_file": "timeseries/b5ed6e96-7490-49c7-bf25-a6148586d543.csv"
}