{
  "run_id": "b90732d0-d6b6-4d3e-a416-b95b2022d44f",
  "timestamp": "2026-05-17T01:54:22.765780",
  "scenario": "ckd_mbd",
  "duration": 3600.0,
  "num_points": 361,
  "environment_params": {
    "Estrogen": 0.5295982655536527,
    "PTH": 158.82335636559137,
    "k_prod_Scl": 1.0708025629015908e-05,
    "k_deg_Scl": 6.681943244446678e-05,
    "Sclerostin_bone": 0.23739185680976013,
    "k_prod_RANKL": 1.655696408633863e-05,
    "k_deg_RANKL": 1.6612046276963923e-05,
    "RANKL_bone": 0.685893883447539,
    "k_prod_OPG": 7.281275279548728e-05,
    "k_deg_OPG": 1.688744175831095e-05,
    "OPG_bone": 2.7094433233016173,
    "MineralIon": 3.0234308806807015,
    "k_prod_Mineral": 0.18831192626335028,
    "k_loss_Mineral": 0.01685685036037162
  },
  "biosensor_config": {
    "circuit_type": "amplifying",
    "sensitivity": 9.610772295678986,
    "threshold": 3.622430666836926e-05,
    "dynamic_range": [
      0.0,
      10.813569316604047
    ],
    "kd": 0.18617930640877206,
    "response_type": "linear",
    "receptor_concentration": 4.738787779053726,
    "enzyme_concentration": 3.2183573914942887,
    "amplification_gain": 7230.7882708647,
    "response_time": 185.67203368128304
  },
  "noise_preset": "high",
  "noise_params": {
    "additive_sigma": 0.08,
    "multiplicative_sigma": 0.12,
    "drift_rate": 0.0004,
    "outlier_probability": 0.005,
    "outlier_magnitude": 6.0,
    "shot_noise_enabled": 0,
    "seed": null
  },
  "measurement": {
    "snr_db": 16.82228944365348,
    "n_detections": 361,
    "detection_rate": 1.0,
    "time_to_detection": 166.9572469621764,
    "false_negative_rate": 0.03819115088779745,
    "max_signal": 16.05473184664887,
    "mean_signal": 11.508441844641167,
    "signal_std": 1.504276812065824,
    "has_noise": 1
  },
  "false_negative_rate": 0.03819115088779745,
  "sclerostin_mean": 2.5331530045741033,
  "sclerostin_max": 2.8680117409587713,
  "sclerostin_min": 0.025000000000000005,
  "sclerostin_std": 0.21380413631153738,
  "metadata_file": "metadata/b90732d0-d6b6-4d3e-a416-b95b2022d44f.json",
  "timeseries_file": "timeseries/b90732d0-d6b6-4d3e-a416-b95b2022d44f.csv"
}