{
  "run_id": "d47292c9-5d91-4cca-bf1d-b5e2b60b2736",
  "timestamp": "2026-05-17T01:48:42.646209",
  "scenario": "ckd_mbd",
  "duration": 3600.0,
  "num_points": 361,
  "environment_params": {
    "Estrogen": 0.6133396347713407,
    "PTH": 212.328860834406,
    "k_prod_Scl": 1.3204495749270844e-05,
    "k_deg_Scl": 6.165635743917415e-05,
    "Sclerostin_bone": 0.1803765561026217,
    "k_prod_RANKL": 2.73280012698596e-05,
    "k_deg_RANKL": 2.1561154055623495e-05,
    "RANKL_bone": 1.1663588674272012,
    "k_prod_OPG": 9.497601665924376e-05,
    "k_deg_OPG": 1.8332944890814995e-05,
    "OPG_bone": 7.2060686694432725,
    "MineralIon": 5.328446401149654,
    "k_prod_Mineral": 0.1317457063659452,
    "k_loss_Mineral": 0.025518078736448145
  },
  "biosensor_config": {
    "circuit_type": "threshold",
    "sensitivity": 7.59332213849895,
    "threshold": 0.0027491852310968304,
    "dynamic_range": [
      0.0,
      7.2672792961202015
    ],
    "kd": 0.24126595274613005,
    "response_type": "linear",
    "hill_coefficient": 3.1270452266570787,
    "off_level": 0.10713449956199836,
    "on_level": 18.384500246536888
  },
  "noise_preset": "high",
  "noise_params": {
    "additive_sigma": 0.08,
    "multiplicative_sigma": 0.12,
    "drift_rate": 0.0004,
    "outlier_probability": 0.005,
    "outlier_magnitude": 6.0,
    "shot_noise_enabled": 0,
    "seed": null
  },
  "measurement": {
    "snr_db": 15.316516296568954,
    "n_detections": 361,
    "detection_rate": 1.0,
    "time_to_detection": 71.39809836740173,
    "false_negative_rate": 0.047355699296697744,
    "max_signal": 10.50548842845923,
    "mean_signal": 7.999835732794258,
    "signal_std": 1.075513920216232,
    "has_noise": 1
  },
  "false_negative_rate": 0.047355699296697744,
  "sclerostin_mean": 2.0091990506369255,
  "sclerostin_max": 2.372896070840813,
  "sclerostin_min": 0.025000000000000005,
  "sclerostin_std": 0.21145403541640503,
  "metadata_file": "metadata/d47292c9-5d91-4cca-bf1d-b5e2b60b2736.json",
  "timeseries_file": "timeseries/d47292c9-5d91-4cca-bf1d-b5e2b60b2736.csv"
}