{
  "run_id": "e8e6db68-1aca-4e27-96b5-de80d9455d93",
  "timestamp": "2026-01-31T04:09:50.290297",
  "scenario": "ckd_mbd",
  "duration": 3600.0,
  "num_points": 361,
  "environment_params": {
    "Estrogen": 0.8961403811596681,
    "PTH": 217.59008145550087,
    "k_prod_Scl": 1.4066023433421259e-05,
    "k_deg_Scl": 3.563013224954692e-05,
    "k_prod_RANKL": 1.941650670438238e-05,
    "k_prod_OPG": 6.675308303390403e-05,
    "Sclerostin_bone": 0.2848902745105316,
    "RANKL_bone": 1.4544660047541533,
    "OPG_bone": 4.564463474430157,
    "MineralIon": 3.2018905060027514,
    "k_prod_Mineral": 0.26017832123404905
  },
  "biosensor_config": {
    "circuit_type": "ratiometric",
    "sensitivity": 3.124833522012203,
    "threshold": 0.001996310112209736,
    "dynamic_range": [
      0.0,
      0.21861676387283765
    ],
    "kd": 0.020282488798064557,
    "response_type": "hill",
    "reference_kd": 0.28217933028574116,
    "ratio_exponent": 0.5953554433688344
  },
  "noise_preset": "medium",
  "noise_params": {
    "additive_sigma": 0.03,
    "multiplicative_sigma": 0.06,
    "drift_rate": 0.0003,
    "outlier_probability": 0.003,
    "outlier_magnitude": 4.0,
    "shot_noise_enabled": false,
    "seed": null
  },
  "measurement": {
    "snr_db": -9.126411594594039,
    "n_detections": 361,
    "detection_rate": 1.0,
    "time_to_detection": 2759.2792580967034,
    "false_negative_rate": 0.0024782611612942196,
    "max_signal": 1.3689507726593744,
    "mean_signal": 0.7581691730969111,
    "signal_std": 0.3158027341601792,
    "has_noise": true
  },
  "false_negative_rate": 0.0024782611612942196,
  "sclerostin_mean": 2.916029764860327,
  "sclerostin_max": 3.149755705408751,
  "sclerostin_min": 0.025000000000000005,
  "sclerostin_std": 0.19129794965143068,
  "metadata_file": "metadata/e8e6db68-1aca-4e27-96b5-de80d9455d93.json",
  "timeseries_file": "timeseries/e8e6db68-1aca-4e27-96b5-de80d9455d93.csv"
}