{
  "run_id": "ee492c96-c57f-47b9-b4d3-a7cbbc6734b9",
  "timestamp": "2026-01-31T04:10:29.278981",
  "scenario": "healthy",
  "duration": 3600.0,
  "num_points": 361,
  "environment_params": {
    "Estrogen": 0.6804879090799655,
    "PTH": 41.58674729115201,
    "k_prod_Scl": 3.561450452223239e-06,
    "k_prod_RANKL": 1.2307232617244485e-05,
    "k_prod_OPG": 0.00016654264275691957,
    "Sclerostin_bone": 0.06507612395175481,
    "RANKL_bone": 0.5889848691780233,
    "OPG_bone": 7.878603206349512
  },
  "biosensor_config": {
    "circuit_type": "ratiometric",
    "sensitivity": 3.2360944765447885,
    "threshold": 0.002429045295305447,
    "dynamic_range": [
      0.0,
      14.381535771406199
    ],
    "kd": 0.04418989847955639,
    "response_type": "hill",
    "reference_kd": 1.231598228289569,
    "ratio_exponent": 2.4754497734829073
  },
  "noise_preset": "high",
  "noise_params": {
    "additive_sigma": 0.1,
    "multiplicative_sigma": 0.2,
    "drift_rate": 0.001,
    "outlier_probability": 0.01,
    "outlier_magnitude": 10.0,
    "shot_noise_enabled": true,
    "seed": null
  },
  "measurement": {
    "snr_db": 3.2835442112035453,
    "n_detections": 361,
    "detection_rate": 1.0,
    "time_to_detection": 718.9013399303129,
    "false_negative_rate": 0.012190386519267727,
    "max_signal": 8.074178167410171,
    "mean_signal": 5.08618802627646,
    "signal_std": 1.2222991545477917,
    "has_noise": true
  },
  "false_negative_rate": 0.012190386519267727,
  "sclerostin_mean": 0.6963577738749703,
  "sclerostin_max": 0.7661543471876853,
  "sclerostin_min": 0.025000000000000005,
  "sclerostin_std": 0.0496470863752526,
  "metadata_file": "metadata/ee492c96-c57f-47b9-b4d3-a7cbbc6734b9.json",
  "timeseries_file": "timeseries/ee492c96-c57f-47b9-b4d3-a7cbbc6734b9.csv"
}