{
  "run_id": "5d3fcdb0-f03f-4d8f-9e9e-8f6f16342f8d",
  "timestamp": "2026-06-27T17:23:18.456744",
  "scenario": "pmo",
  "biosensor_config": {
    "circuit_type": "array",
    "kd_scl": 6.945875234977355,
    "kd_ctx": 0.1049981188796177,
    "kd_p1np": 4.115629106470217,
    "w_scl": 0.4573666520939072,
    "w_ctx": 0.26234138001657387,
    "w_p1np": 0.28029196788951893,
    "sensitivity": 2.1052527554931513,
    "threshold": 3.022978790721829,
    "dynamic_range": [
      0.0,
      8.617715697383863
    ],
    "kd": 6.945875234977355
  },
  "noise_preset": "realistic",
  "measurement": {
    "snr_db": 13.881763187039136,
    "n_detections": 1,
    "detection_rate": 1.0,
    "time_to_detection": 1680.0,
    "false_negative_rate": 0.0
  },
  "environment_params": {
    "Estrogen": 0.2273899982745068,
    "PTH": 65.79585300898428,
    "k_prod_Scl": 5.91730629372983e-07,
    "k_deg_Scl": 6.430807453693566e-05,
    "Sclerostin_bone": 0.03171446086742936,
    "k_prod_RANKL": 3.1858484517077186e-06,
    "k_deg_RANKL": 2.2703723860206773e-05,
    "RANKL_bone": 0.8764427904787554,
    "k_prod_OPG": 5.494524641323985e-05,
    "k_deg_OPG": 2.0437785629941064e-05,
    "OPG_bone": 5.397777916459902,
    "MineralIon": 2.9447810790943363,
    "k_prod_Mineral": 0.06581995533251046,
    "k_loss_Mineral": 0.02395565434638778,
    "k_prod_CTX": 6.625943516269761e-07,
    "k_deg_CTX": 2.213054039165329e-05,
    "CTX_bone": 0.015927974699517143,
    "k_prod_P1NP": 1.9512685459608668e-07,
    "k_deg_P1NP": 2.3195347494627746e-05,
    "P1NP_bone": 0.019463676978925603,
    "Sclerostin_sensor": 0.792861521685734,
    "RANKL_sensor": 26.293283714362662,
    "OPG_sensor": 161.93333749379707,
    "CTX_sensor": 0.39819936748792856,
    "P1NP_sensor": 0.4865919244731401
  },
  "equilibration_check": {
    "Sclerostin_bone": 0.00024381404282567207,
    "RANKL_bone": 0.00016534865516601408,
    "OPG_bone": 0.00020298700897345657,
    "CTX_bone": 0.00023293993416176735,
    "P1NP_bone": 9.74615718174825e-05,
    "Osteocytes": 4.910176169925988e-05,
    "Osteoblasts": 1.4450459123731236e-06,
    "Osteoclasts": 6.994301687672646e-05,
    "MineralIon": 1.4367958528607847e-06,
    "Sclerostin_sensor": 0.00024397042230263965,
    "RANKL_sensor": 0.00016541747929156112,
    "OPG_sensor": 0.00020305257419910266,
    "CTX_sensor": 0.00023300264172586182,
    "P1NP_sensor": 9.748983013993315e-05
  },
  "sclerostin_mean": 0.7884574985977337,
  "sclerostin_max": 0.7917731640391458,
  "sclerostin_min": 0.7851831610236865,
  "sclerostin_std": 0.001909173017539608,
  "ctx_mean": 0.39608297350309374,
  "p1np_mean": 0.48552085782397053,
  "metadata_file": "metadata/5d3fcdb0-f03f-4d8f-9e9e-8f6f16342f8d.json",
  "timeseries_file": "timeseries/5d3fcdb0-f03f-4d8f-9e9e-8f6f16342f8d.csv",
  "instrumentation": {
    "biological_realization": {
      "rng_seed": 376952384,
      "scenario": "pmo",
      "realization_hash": "bab34ae8421ec349"
    },
    "stages": {
      "stage_0_ode": {
        "stage": "stage_0_ode",
        "description": "ODE concentration output",
        "mean_signal": 0.7884574985977337,
        "std_signal": 0.001909173017539608,
        "min_signal": 0.7851831610236865,
        "max_signal": 0.7917731640391458,
        "median_signal": 0.7884467764719866,
        "q25_signal": 0.7868049679164749,
        "q75_signal": 0.7901048523333635,
        "auc_total": 2838.446788312505,
        "auc_per_second": 0.788457441197918,
        "terminal_mean": 0.7854969704761944,
        "terminal_std": 0.0001864428634802476,
        "signal_range": 0.0065900030154593114,
        "cv_coefficient": 0.002421402575199119,
        "species_tracked": "Sclerostin_sensor or Sclerostin_bone"
      },
      "stage_1_biosensor_clean": {
        "stage": "stage_1_biosensor_clean",
        "description": "Biosensor output (clean signal, no noise)",
        "mean_signal": 3.37648092647708,
        "std_signal": 0.005169600405780901,
        "min_signal": 3.367606436171729,
        "max_signal": 3.385453222653896,
        "median_signal": 3.3764555691119496,
        "q25_signal": 3.3720076884350165,
        "q75_signal": 3.3809418875882233,
        "auc_total": 12155.330846288129,
        "auc_per_second": 3.376480790635591,
        "terminal_mean": 3.3684586551575126,
        "terminal_std": 0.000506263229256381,
        "signal_range": 0.017846786482166976,
        "cv_coefficient": 0.001531061634390664,
        "biosensor_type": "array",
        "kd": 6.945875234977355,
        "sensitivity": 2.1052527554931513
      },
      "stage_2_biosensor_noisy": {
        "stage": "stage_2_biosensor_noisy",
        "description": "Biosensor output (with noise injection)",
        "mean_signal": 3.447760443789553,
        "std_signal": 0.6788418036833692,
        "min_signal": 1.4953129413115145,
        "max_signal": 5.534617686304822,
        "median_signal": 3.438044564265187,
        "q25_signal": 2.96032858588575,
        "q75_signal": 3.883280344326006,
        "auc_total": 12409.341236717944,
        "auc_per_second": 3.4470392324216514,
        "terminal_mean": 3.4293384748788047,
        "terminal_std": 0.6876958797194102,
        "signal_range": 4.0393047449933075,
        "cv_coefficient": 0.1968935530037089,
        "noise_preset": "realistic",
        "snr_db": 13.881763187039136
      },
      "stage_3_thresholded": {
        "stage": "stage_3_thresholded",
        "description": "Threshold crossing detection",
        "threshold": 3.022978790721829,
        "fraction_above_threshold": 0.7202216066481995,
        "time_to_first_crossing": 0.0,
        "n_threshold_crossings": 159,
        "mean_signal_above": 3.7558999413475784,
        "std_signal_above": 0.512507887294145,
        "mean_signal_below": 2.6545300540362207,
        "std_signal_below": 0.31193872599073,
        "mean_margin_above_threshold": 0.7329211506257491,
        "mean_margin_below_threshold": -0.36844873668560824
      },
      "stage_4_ttd": {
        "stage": "stage_4_ttd",
        "description": "Time-to-detection assignment",
        "ttd_seconds": 1680.0,
        "detected": true,
        "is_sentinel": false
      }
    },
    "stage_deltas": {
      "delta_0_to_1": {
        "transition": "stage_0_ode->stage_1_biosensor_clean",
        "mean_delta": 2.5880234278793464,
        "std_delta": 0.003260427994394194,
        "max_delta": 2.59368005861475,
        "rms_delta": 2.588025481644852,
        "fraction_significantly_changed": 1.0
      },
      "delta_1_to_2": {
        "transition": "stage_1_biosensor_clean->stage_2_biosensor_noisy",
        "mean_delta": 0.07127951731247309,
        "std_delta": 0.6791999034398363,
        "max_delta": 2.1556238804923042,
        "rms_delta": 0.6829299220425052,
        "fraction_significantly_changed": 1.0
      },
      "delta_2_to_3": {
        "transition": "stage_2_biosensor_noisy->stage_3_thresholded",
        "mean_delta": -0.7426801536223221,
        "std_delta": 1.202961773870354,
        "max_delta": 3.0184748284108758,
        "rms_delta": 1.4137506286392183,
        "fraction_significantly_changed": 0.27977839335180055
      }
    },
    "propagation_integrity": {
      "stages_recorded": 5,
      "biological_hash_consistent": false,
      "all_stages_use_same_time": true
    }
  }
}